xlwings_macos_utils/__init__.py
xlwings_macos_utils/core.py
xlwings_macos_utils-0.1.0.dist-info/licenses/LICENSE
xlwings_macos_utils-0.1.0.dist-info/METADATA
xlwings_macos_utils-0.1.0.dist-info/WHEEL
xlwings_macos_utils-0.1.0.dist-info/top_level.txt
xlwings_macos_utils-0.1.0.dist-info/RECORD
