Metadata-Version: 2.4
Name: xlwings-macos-utils
Version: 0.1.0
Summary: Utilities to solve macOS-specific issues with xlwings automation
Author-email: Andre Galvão <andreggalvao@gmail.com>
License: MIT
Project-URL: Homepage, https://github.com/andreggalvao/xlwings-macos-utils
Project-URL: Documentation, https://github.com/andreggalvao/xlwings-macos-utils#readme
Project-URL: Repository, https://github.com/andreggalvao/xlwings-macos-utils
Project-URL: Issues, https://github.com/andreggalvao/xlwings-macos-utils/issues
Keywords: xlwings,macos,excel,automation,workaround
Classifier: Development Status :: 4 - Beta
Classifier: Intended Audience :: Developers
Classifier: License :: OSI Approved :: MIT License
Classifier: Operating System :: MacOS
Classifier: Programming Language :: Python :: 3
Classifier: Programming Language :: Python :: 3.8
Classifier: Programming Language :: Python :: 3.9
Classifier: Programming Language :: Python :: 3.10
Classifier: Programming Language :: Python :: 3.11
Classifier: Programming Language :: Python :: 3.12
Classifier: Topic :: Office/Business
Classifier: Topic :: Software Development :: Libraries :: Python Modules
Requires-Python: >=3.8
License-File: LICENSE
Requires-Dist: xlwings>=0.27.0
Provides-Extra: dev
Requires-Dist: pytest>=7.0.0; extra == "dev"
Requires-Dist: pytest-cov>=4.0.0; extra == "dev"
Requires-Dist: pytest-mock>=3.10.0; extra == "dev"
Requires-Dist: ruff>=0.1.0; extra == "dev"
Dynamic: license-file
